app/__init__.py
app/dash_app.py
app/server.py
app/server_client.py
app/streamlit_app.py
app/utils.py
chemeleon/__init__.py
chemeleon/cli.py
chemeleon/config.py
chemeleon/constants.py
chemeleon/datamodule.py
chemeleon/visualize.py
chemeleon/datasets/__init__.py
chemeleon/datasets/dataset_utils.py
chemeleon/datasets/mp_dataset.py
chemeleon/modules/__init__.py
chemeleon/modules/base_module.py
chemeleon/modules/chemeleon.py
chemeleon/modules/cspnet.py
chemeleon/modules/schema.py
chemeleon/scripts/__init__.py
chemeleon/scripts/evaluate.py
chemeleon/scripts/navigate_chemical_system.py
chemeleon/scripts/optimize.py
chemeleon/scripts/sample_prompt.py
chemeleon/scripts/sample_target_composition.py
chemeleon/text_encoder/__init__.py
chemeleon/text_encoder/crystal_clip.py
chemeleon/text_encoder/text_encoder.py
chemeleon/utils/__init__.py
chemeleon/utils/data_utils.py
chemeleon/utils/diff_utils.py
chemeleon/utils/download.py
chemeleon/utils/scatter.py
chemeleon-0.1.3.dist-info/licenses/LICENSE
chemeleon-0.1.3.dist-info/METADATA
chemeleon-0.1.3.dist-info/WHEEL
chemeleon-0.1.3.dist-info/entry_points.txt
chemeleon-0.1.3.dist-info/top_level.txt
chemeleon-0.1.3.dist-info/RECORD
