Metadata-Version: 2.4
Name: chemeleon
Version: 0.1.3
Summary: A Text-guided Crystal Structure Generation Model
Author: Hyunsoo Park
Author-email: phs68660888@gmail.com
License-File: LICENSE
Requires-Dist: torch>=2.1.0
Requires-Dist: pytorch-lightning>=2.1.0
Requires-Dist: smact>=3.1.0
Requires-Dist: torch-geometric
Requires-Dist: torchmetrics
Requires-Dist: streamlit
Requires-Dist: dash
Requires-Dist: ase
Requires-Dist: tqdm
Requires-Dist: wandb
Requires-Dist: click
Requires-Dist: fire
Requires-Dist: transformers
Requires-Dist: pydantic
Requires-Dist: einops
Requires-Dist: jupyterlab
Requires-Dist: pymatgen
Dynamic: author
Dynamic: author-email
Dynamic: description
Dynamic: description-content-type
Dynamic: license-file
Dynamic: requires-dist
Dynamic: summary
